pprint_ordered_sets.py
pprint_ordered_sets-1.0.0.dist-info/LICENSE
pprint_ordered_sets-1.0.0.dist-info/WHEEL
pprint_ordered_sets-1.0.0.dist-info/METADATA
pprint_ordered_sets-1.0.0.dist-info/RECORD
