Metadata-Version: 2.1
Name: pprint-ordered-sets
Version: 1.0.0
Summary: The standard library pprint module, but sets are always ordered.
Home-page: https://github.com/bbonenfant/pprint_ordered_sets
License: MIT
Keywords: pprint,sets
Author: Ben Bonenfant
Author-email: bonenfan5ben@gmail.com
Requires-Python: >=3.6.1,<4.0.0
Classifier: License :: OSI Approved :: MIT License
Classifier: License :: OSI Approved :: Python Software Foundation License
Classifier: Operating System :: OS Independent
Classifier: Programming Language :: Python :: 3
Classifier: Programming Language :: Python :: 3.7
Classifier: Programming Language :: Python :: 3.8
Project-URL: Repository, https://github.com/bbonenfant/pprint_ordered_sets
